{
    "id": 80258032,
    "name": "2 0 1 3",
    "author": "xThundra",
    "creators": ["0rd3n4ry, KrazyGFX, TheHuevon, Lezick, KimMii, JairoFx, Zafkiel7, nsMonsteR, Viper Arctarus, Astrofox, Astraa, AlmanzaAR, Ashene, boii, Dax, Rolex, Lerixon, Diris, Venoth, TheAhiyu, TheElectro, xThundra, AppleCr, fjscope, Liuxe, MDJr, Genoxium, StevStyles, N3MO, iMeox"],
    "verifier": "TheAhiyu",
    "verification": "https://www.youtube.com/watch?v=dXlgTJQbQH0",
    "showcase": "https://www.youtube.com/watch?v=qU4EG_z3pws",
    "percentToQualify": 66,
    "password": "Free Copy",
    "records": [
    ]
}
