{
    "id": 126269202,
    "name": "Krypton",
    "author": "Livyoshi",
    "creators": ["sylveonenjoyer, SeasickK, Poishy, DjackV, skuvv, Velanidi, tiburones202, kobbob7, kowariclaws, definitive64, undercookedwaffle, nover, YPerm, Zoomifly, CircularCyclone"],
    "verifier": "Livyoshi",
    "verification": "https://www.youtube.com/watch?v=UUo2jRFdXzw",
    "showcase": "https://www.youtube.com/watch?v=OeBKQ_Xk3t0",
    "percentToQualify": 66,
    "password": "Free Copy",
    "records": [
    ]
}
